{
  "metadata": {
    "name": "CricHD Channels Playlist",
    "description": "Automatically generated CricHD playlist channels",
    "version": "1.0.0",
    "developer": "@sultanarabi 161 —  credit: Toufik bro@",
    "country": "Bangladesh",
    "last_update_utc": "2025-10-27T13:58:25.670607+00:00",
    "last_update_bd": "2025-10-27 13:58:25 UTC",
    "total_channels": 28
  },
  "channels": [
    {
      "tvg-id": "ptvpk",
      "tvg-logo": "https://raw.githubusercontent.com/abusaeeidx/Tv-Channel-Logo/heads/main/CricHD/runded/20-by-xfireflix.png",
      "name": "PTV Sports",
      "url": "https://d2.merichunidya.com:1686/hls/ptvpk.m3u8?md5=DXawzZH2BaxFrQz-tfVvYg&expires=1761580651"
    },
    {
      "tvg-id": "sonyten1",
      "tvg-logo": "https://raw.githubusercontent.com/abusaeeidx/Tv-Channel-Logo/heads/main/CricHD/runded/1000173192-modified.png",
      "name": "Tony Sports 1",
      "url": "https://d3.merichunidya.com:1686/hls/ten1hd.m3u8?md5=FkIvbsaf33bOiZaM-4cUUQ&expires=1761580652"
    },
    {
      "tvg-id": "willowusa",
      "tvg-logo": "https://raw.githubusercontent.com/abusaeeidx/Tv-Channel-Logo/heads/main/CricHD/runded/38-by-xfireflix.png",
      "name": "Willow Cricket",
      "url": "https://d5.merichunidya.com:1686/hls/willowusa.m3u8?md5=NXEioGlswKXMulUiehs0-A&expires=1761580651"
    },
    {
      "tvg-id": "tensp",
      "tvg-logo": "https://raw.githubusercontent.com/abusaeeidx/Tv-Channel-Logo/heads/main/CricHD/runded/10-by-xfireflix.png",
      "name": "Ten Sports PK",
      "url": "https://d9.merichunidya.com:1686/hls/tenspk.m3u8?md5=id2PoQcr_6XqpnESho9kZw&expires=1761580651"
    },
    {
      "tvg-id": "asportshd",
      "tvg-logo": "https://raw.githubusercontent.com/abusaeeidx/Tv-Channel-Logo/heads/main/CricHD/runded/12-by-xfireflix.png",
      "name": "A Sports HD",
      "url": "https://d1.merichunidya.com:1686/hls/asportshd.m3u8?md5=N_djzl35zSybCML5BGF8jA&expires=1761580651"
    },
    {
      "tvg-id": "tonymax",
      "tvg-logo": "https://raw.githubusercontent.com/abusaeeidx/Tv-Channel-Logo/heads/main/CricHD/runded/1000173192-modified.png",
      "name": "Tony Sports 3",
      "url": "https://d4.merichunidya.com:1686/hls/sonyespnind.m3u8?md5=PLFOYoRBYPgkpwzBR491Eg&expires=1761580651"
    },
    {
      "tvg-id": "sscricket",
      "tvg-logo": "https://raw.githubusercontent.com/abusaeeidx/Tv-Channel-Logo/heads/main/CricHD/runded/34-by-xfireflix.png",
      "name": "Super Cricket",
      "url": "https://d2.merichunidya.com:1686/hls/supercricket.m3u8?md5=jMubflg0_XddKNF7NO9NXw&expires=1761580651"
    },
    {
      "tvg-id": "skys2",
      "tvg-logo": "https://raw.githubusercontent.com/abusaeeidx/Tv-Channel-Logo/heads/main/CricHD/runded/9-by-xfireflix.png",
      "name": "Sky Sports Cricket",
      "url": "https://d1.merichunidya.com:1686/hls/skyscric.m3u8?md5=DLR2cX6zKIey1N_5UvlnRA&expires=1761580651"
    },
    {
      "tvg-id": "btsp4",
      "tvg-logo": "https://raw.githubusercontent.com/abusaeeidx/Tv-Channel-Logo/heads/main/CricHD/runded/tnt.png",
      "name": "BT Sports 4",
      "url": "https://d10.merichunidya.com:1686/hls/bbtespn.m3u8?md5=rD20Qs5QsUnLClAmr-Ij4g&expires=1761580653"
    },
    {
      "tvg-id": "btsp3",
      "tvg-logo": "https://raw.githubusercontent.com/abusaeeidx/Tv-Channel-Logo/heads/main/CricHD/runded/tnt.png",
      "name": "BT Sports 3",
      "url": "https://d5.merichunidya.com:1686/hls/bbtsp3.m3u8?md5=K5KnfRs6wcMQ1yOxlGUJeA&expires=1761580652"
    },
    {
      "tvg-id": "btsp1",
      "tvg-logo": "https://raw.githubusercontent.com/abusaeeidx/Tv-Channel-Logo/heads/main/CricHD/runded/tnt.png",
      "name": "BT Sports 1",
      "url": "https://d2.merichunidya.com:1686/hls/bbtsp1.m3u8?md5=Mmvzhf24lzBc97bPv4zMcg&expires=1761580651"
    },
    {
      "tvg-id": "btsp2",
      "tvg-logo": "https://raw.githubusercontent.com/abusaeeidx/Tv-Channel-Logo/heads/main/CricHD/runded/tnt.png",
      "name": "BT Sports 2",
      "url": "https://d6.merichunidya.com:1686/hls/bbtsp2.m3u8?md5=E9wCsqE__R28eWeXYemuZw&expires=1761580651"
    },
    {
      "tvg-id": "willo2",
      "tvg-logo": "https://raw.githubusercontent.com/abusaeeidx/Tv-Channel-Logo/heads/main/CricHD/runded/8-by-xfireflix.png",
      "name": "Willow 2",
      "url": null
    },
    {
      "tvg-id": "fox501",
      "tvg-logo": "https://raw.githubusercontent.com/abusaeeidx/Tv-Channel-Logo/heads/main/CricHD/runded/6-by-xfireflix.png",
      "name": "FOX Cricket 501",
      "url": "https://d8.merichunidya.com:1686/hls/fox501.m3u8?md5=ZY92SIIc6ZGnYzOA8b7qVw&expires=1761580651"
    },
    {
      "tvg-id": "skys1",
      "tvg-logo": "https://raw.githubusercontent.com/abusaeeidx/Tv-Channel-Logo/heads/main/CricHD/runded/18-by-xfireflix.png",
      "name": "Sky Sports Main Event",
      "url": "https://d2.merichunidya.com:1686/hls/skysme.m3u8?md5=414HiafFXR5adl3l36HQxQ&expires=1761580652"
    },
    {
      "tvg-id": "viasp1",
      "tvg-logo": "https://raw.githubusercontent.com/abusaeeidx/Tv-Channel-Logo/heads/main/CricHD/runded/31-by-xfireflix.png",
      "name": "Via Play Sports 1",
      "url": "https://d7.merichunidya.com:1686/hls/premieruk.m3u8?md5=PVdeN_TnwA_mcItuttqPLw&expires=1761580651"
    },
    {
      "tvg-id": "btsp5",
      "tvg-logo": "https://raw.githubusercontent.com/abusaeeidx/Tv-Channel-Logo/heads/main/CricHD/runded/tnt.png",
      "name": "BT Sports 5",
      "url": "https://d8.merichunidya.com:1686/hls/hdchnl10.m3u8?md5=aiiPM_25NrVy0ny2828pAA&expires=1761580651"
    },
    {
      "tvg-id": "tara",
      "tvg-logo": "https://raw.githubusercontent.com/abusaeeidx/Tv-Channel-Logo/heads/main/CricHD/runded/16-by-xfireflix.png",
      "name": " Tara Sports 1",
      "url": "https://d10.merichunidya.com:1686/hls/star1in.m3u8?md5=-AYyAyOifGT6ZVYOu7i2Zg&expires=1761580651"
    },
    {
      "tvg-id": "tara1hi",
      "tvg-logo": "https://raw.githubusercontent.com/abusaeeidx/Tv-Channel-Logo/heads/main/CricHD/runded/1-by-xfireflix.png",
      "name": " Tara Sports Hindi",
      "url": "https://d6.merichunidya.com:1686/hls/starhindi.m3u8?md5=QXuSqRRGADvsErU0yyeSbg&expires=1761580652"
    },
    {
      "tvg-id": "sky1nz",
      "tvg-logo": "https://raw.githubusercontent.com/abusaeeidx/Tv-Channel-Logo/heads/main/CricHD/runded/56-by-xfireflix.png",
      "name": " Sky Sport 1 NZ",
      "url": "https://d10.merichunidya.com:1686/hls/sky1nz.m3u8?md5=NaQSPUCRB2zgasveuNInxw&expires=1761580651"
    },
    {
      "tvg-id": "sky2nz",
      "tvg-logo": "https://raw.githubusercontent.com/abusaeeidx/Tv-Channel-Logo/heads/main/CricHD/runded/56-by-xfireflix.png",
      "name": " Sky Sport 2 NZ",
      "url": "https://d2.merichunidya.com:1686/hls/sky2nz.m3u8?md5=KoEM5jZ3Q1gyc2J8dQHhwA&expires=1761580651"
    },
    {
      "tvg-id": "sky3nz",
      "tvg-logo": "https://raw.githubusercontent.com/abusaeeidx/Tv-Channel-Logo/heads/main/CricHD/runded/56-by-xfireflix.png",
      "name": " Sky Sport 3 NZ",
      "url": "https://d7.merichunidya.com:1686/hls/sky3nz.m3u8?md5=f8LNC4rh3LbJUzsi0niU6w&expires=1761580651"
    },
    {
      "tvg-id": "sky4nz",
      "tvg-logo": "https://raw.githubusercontent.com/abusaeeidx/Tv-Channel-Logo/heads/main/CricHD/runded/56-by-xfireflix.png",
      "name": " Sky Sport 4 NZ",
      "url": "https://d6.merichunidya.com:1686/hls/sky4nz.m3u8?md5=pqnTUFcbPWxGoGXezrSxBQ&expires=1761580651"
    },
    {
      "tvg-id": "sky5nz",
      "tvg-logo": "https://raw.githubusercontent.com/abusaeeidx/Tv-Channel-Logo/heads/main/CricHD/runded/56-by-xfireflix.png",
      "name": " Sky Sport 5 NZ",
      "url": "https://d10.merichunidya.com:1686/hls/sky5nz.m3u8?md5=_pIMifi3LZMWsMe8qfwJwQ&expires=1761580651"
    },
    {
      "tvg-id": "sky6nz",
      "tvg-logo": "https://raw.githubusercontent.com/abusaeeidx/Tv-Channel-Logo/heads/main/CricHD/runded/56-by-xfireflix.png",
      "name": " Sky Sport 6 NZ",
      "url": "https://d8.merichunidya.com:1686/hls/sky6nz.m3u8?md5=9ft_Mpqt0Ln0rR1Wajjv6A&expires=1761580651"
    },
    {
      "tvg-id": "sky7nz",
      "tvg-logo": "https://raw.githubusercontent.com/abusaeeidx/Tv-Channel-Logo/heads/main/CricHD/runded/56-by-xfireflix.png",
      "name": " Sky Sport 7 NZ",
      "url": "https://d2.merichunidya.com:1686/hls/sky7nz.m3u8?md5=2u53XKFWDqJ1dJ3fS1_SHg&expires=1761580651"
    },
    {
      "tvg-id": "sky8nz",
      "tvg-logo": "https://raw.githubusercontent.com/abusaeeidx/Tv-Channel-Logo/heads/main/CricHD/runded/56-by-xfireflix.png",
      "name": " Sky Sport 8 NZ",
      "url": "https://d6.merichunidya.com:1686/hls/sky8nz.m3u8?md5=uCsmmQGww8G37XqelLYxng&expires=1761580652"
    },
    {
      "tvg-id": "laligauk",
      "tvg-logo": "https://raw.githubusercontent.com/abusaeeidx/Tv-Channel-Logo/heads/main/CricHD/runded/19-by-xfireflix.png",
      "name": "LaLiga UK",
      "url": "https://d4.merichunidya.com:1686/hls/laligauk.m3u8?md5=R02uQ1nRSIg3XEmRZJZUFg&expires=1761580651"
    },
    {
      "tvg-id": "skysfotb",
      "tvg-logo": "https://raw.githubusercontent.com/abusaeeidx/Tv-Channel-Logo/heads/main/CricHD/runded/44-by-xfireflix.png",
      "name": " Sky Sports Football",
      "url": "https://d10.merichunidya.com:1686/hls/skysfott.m3u8?md5=SZdzoFbtSXpFXMySScPCng&expires=1761580651"
    },
    {
      "tvg-id": "hdchnl2",
      "tvg-logo": "https://raw.githubusercontent.com/abusaeeidx/Tv-Channel-Logo/heads/main/CricHD/runded/31-by-xfireflix.png",
      "name": " Premier Sports 2",
      "url": null
    }
  ]
}