{
  "metadata": {
    "name": "CricHD Channels Playlist",
    "description": "Automatically generated CricHD playlist channels",
    "version": "1.0.0",
    "developer": "@sultanarabi 161 —  credit: Toufik bro@",
    "country": "Bangladesh",
    "last_update_utc": "2025-10-31T20:55:22.648426+00:00",
    "last_update_bd": "2025-10-31 20:55:22 UTC",
    "total_channels": 28
  },
  "channels": [
    {
      "tvg-id": "ptvpk",
      "tvg-logo": "https://raw.githubusercontent.com/abusaeeidx/Tv-Channel-Logo/heads/main/CricHD/runded/20-by-xfireflix.png",
      "name": "PTV Sports",
      "url": "https://d11.epicquesthero.com:999/hls/ptvpk.m3u8?md5=js-yR0wJ5P-kCBrk3r1ylQ&expires=1761951301"
    },
    {
      "tvg-id": "sonyten1",
      "tvg-logo": "https://raw.githubusercontent.com/abusaeeidx/Tv-Channel-Logo/heads/main/CricHD/runded/1000173192-modified.png",
      "name": "Tony Sports 1",
      "url": "https://d11.epicquesthero.com:999/hls/ten1hd.m3u8?md5=57CkXgaCJeG-OSfQQ82M9g&expires=1761951301"
    },
    {
      "tvg-id": "willowusa",
      "tvg-logo": "https://raw.githubusercontent.com/abusaeeidx/Tv-Channel-Logo/heads/main/CricHD/runded/38-by-xfireflix.png",
      "name": "Willow Cricket",
      "url": "https://d12.epicquesthero.com:999/hls/willowusa.m3u8?md5=gLEzIEdTAH_yK0kKbUnraA&expires=1761951298"
    },
    {
      "tvg-id": "tensp",
      "tvg-logo": "https://raw.githubusercontent.com/abusaeeidx/Tv-Channel-Logo/heads/main/CricHD/runded/10-by-xfireflix.png",
      "name": "Ten Sports PK",
      "url": "https://d12.epicquesthero.com:999/hls/tenspk.m3u8?md5=GdqWbEhtY5v4BZkX7sPAZQ&expires=1761951301"
    },
    {
      "tvg-id": "asportshd",
      "tvg-logo": "https://raw.githubusercontent.com/abusaeeidx/Tv-Channel-Logo/heads/main/CricHD/runded/12-by-xfireflix.png",
      "name": "A Sports HD",
      "url": "https://d11.epicquesthero.com:999/hls/asportshd.m3u8?md5=MkSiZSzXdrTOgdQ-9mV8ig&expires=1761951301"
    },
    {
      "tvg-id": "tonymax",
      "tvg-logo": "https://raw.githubusercontent.com/abusaeeidx/Tv-Channel-Logo/heads/main/CricHD/runded/1000173192-modified.png",
      "name": "Tony Sports 3",
      "url": "https://d12.epicquesthero.com:999/hls/sonyespnind.m3u8?md5=aN-vNaio0NPxPqSBvHLxBA&expires=1761951301"
    },
    {
      "tvg-id": "sscricket",
      "tvg-logo": "https://raw.githubusercontent.com/abusaeeidx/Tv-Channel-Logo/heads/main/CricHD/runded/34-by-xfireflix.png",
      "name": "Super Cricket",
      "url": "https://d13.epicquesthero.com:999/hls/supercricket.m3u8?md5=qdcPWFHBY9TwN9PfwWCNkQ&expires=1761951301"
    },
    {
      "tvg-id": "skys2",
      "tvg-logo": "https://raw.githubusercontent.com/abusaeeidx/Tv-Channel-Logo/heads/main/CricHD/runded/9-by-xfireflix.png",
      "name": "Sky Sports Cricket",
      "url": "https://d13.epicquesthero.com:999/hls/skyscric.m3u8?md5=dCYZ4yEKs4hkbfqBYPIJkQ&expires=1761951301"
    },
    {
      "tvg-id": "btsp4",
      "tvg-logo": "https://raw.githubusercontent.com/abusaeeidx/Tv-Channel-Logo/heads/main/CricHD/runded/tnt.png",
      "name": "BT Sports 4",
      "url": "https://d14.epicquesthero.com:999/hls/bbtespn.m3u8?md5=kjM4qqY0OVSDWW0Pb30-XQ&expires=1761951301"
    },
    {
      "tvg-id": "btsp3",
      "tvg-logo": "https://raw.githubusercontent.com/abusaeeidx/Tv-Channel-Logo/heads/main/CricHD/runded/tnt.png",
      "name": "BT Sports 3",
      "url": "https://d15.epicquesthero.com:999/hls/bbtsp3.m3u8?md5=QmMqloHEsaMZ6JhElp9X_A&expires=1761951301"
    },
    {
      "tvg-id": "btsp1",
      "tvg-logo": "https://raw.githubusercontent.com/abusaeeidx/Tv-Channel-Logo/heads/main/CricHD/runded/tnt.png",
      "name": "BT Sports 1",
      "url": "https://d14.epicquesthero.com:999/hls/bbtsp1.m3u8?md5=aqy-HUecYk7-2C58yNhENg&expires=1761951300"
    },
    {
      "tvg-id": "btsp2",
      "tvg-logo": "https://raw.githubusercontent.com/abusaeeidx/Tv-Channel-Logo/heads/main/CricHD/runded/tnt.png",
      "name": "BT Sports 2",
      "url": "https://d13.epicquesthero.com:999/hls/bbtsp2.m3u8?md5=BOYYy_bHBP3cDyUSguN6oA&expires=1761951301"
    },
    {
      "tvg-id": "willo2",
      "tvg-logo": "https://raw.githubusercontent.com/abusaeeidx/Tv-Channel-Logo/heads/main/CricHD/runded/8-by-xfireflix.png",
      "name": "Willow 2",
      "url": null
    },
    {
      "tvg-id": "fox501",
      "tvg-logo": "https://raw.githubusercontent.com/abusaeeidx/Tv-Channel-Logo/heads/main/CricHD/runded/6-by-xfireflix.png",
      "name": "FOX Cricket 501",
      "url": "https://d12.epicquesthero.com:999/hls/fox501.m3u8?md5=W3YBMcwhfRPPsSJq6h3qSw&expires=1761951301"
    },
    {
      "tvg-id": "skys1",
      "tvg-logo": "https://raw.githubusercontent.com/abusaeeidx/Tv-Channel-Logo/heads/main/CricHD/runded/18-by-xfireflix.png",
      "name": "Sky Sports Main Event",
      "url": "https://d15.epicquesthero.com:999/hls/skysme.m3u8?md5=lmgpdy7dYYlB767q2wjqZw&expires=1761951301"
    },
    {
      "tvg-id": "viasp1",
      "tvg-logo": "https://raw.githubusercontent.com/abusaeeidx/Tv-Channel-Logo/heads/main/CricHD/runded/31-by-xfireflix.png",
      "name": "Via Play Sports 1",
      "url": "https://d12.epicquesthero.com:999/hls/premieruk.m3u8?md5=QmL1NksZ1Euja_GcmMC8Cw&expires=1761951301"
    },
    {
      "tvg-id": "btsp5",
      "tvg-logo": "https://raw.githubusercontent.com/abusaeeidx/Tv-Channel-Logo/heads/main/CricHD/runded/tnt.png",
      "name": "BT Sports 5",
      "url": "https://d14.epicquesthero.com:999/hls/hdchnl10.m3u8?md5=HAcRnX0LHFp92-AY3Aj3tQ&expires=1761951301"
    },
    {
      "tvg-id": "tara",
      "tvg-logo": "https://raw.githubusercontent.com/abusaeeidx/Tv-Channel-Logo/heads/main/CricHD/runded/16-by-xfireflix.png",
      "name": " Tara Sports 1",
      "url": "https://d13.epicquesthero.com:999/hls/star1in.m3u8?md5=m_d3-PIPBLZ4l5lsWq1QWw&expires=1761951301"
    },
    {
      "tvg-id": "tara1hi",
      "tvg-logo": "https://raw.githubusercontent.com/abusaeeidx/Tv-Channel-Logo/heads/main/CricHD/runded/1-by-xfireflix.png",
      "name": " Tara Sports Hindi",
      "url": "https://d11.epicquesthero.com:999/hls/starhindi.m3u8?md5=3pRsNOafkN4gs2f0uIqF-w&expires=1761951301"
    },
    {
      "tvg-id": "sky1nz",
      "tvg-logo": "https://raw.githubusercontent.com/abusaeeidx/Tv-Channel-Logo/heads/main/CricHD/runded/56-by-xfireflix.png",
      "name": " Sky Sport 1 NZ",
      "url": "https://d14.epicquesthero.com:999/hls/sky1nz.m3u8?md5=z-o1eR3DZgE4gQ3Aiaw3aw&expires=1761951301"
    },
    {
      "tvg-id": "sky2nz",
      "tvg-logo": "https://raw.githubusercontent.com/abusaeeidx/Tv-Channel-Logo/heads/main/CricHD/runded/56-by-xfireflix.png",
      "name": " Sky Sport 2 NZ",
      "url": "https://d15.epicquesthero.com:999/hls/sky2nz.m3u8?md5=6mJkQE1YJLfQRjtQcpXMSg&expires=1761951301"
    },
    {
      "tvg-id": "sky3nz",
      "tvg-logo": "https://raw.githubusercontent.com/abusaeeidx/Tv-Channel-Logo/heads/main/CricHD/runded/56-by-xfireflix.png",
      "name": " Sky Sport 3 NZ",
      "url": "https://d12.epicquesthero.com:999/hls/sky3nz.m3u8?md5=jot3_YHYA0xKZYhVy4bQxA&expires=1761951301"
    },
    {
      "tvg-id": "sky4nz",
      "tvg-logo": "https://raw.githubusercontent.com/abusaeeidx/Tv-Channel-Logo/heads/main/CricHD/runded/56-by-xfireflix.png",
      "name": " Sky Sport 4 NZ",
      "url": "https://d11.epicquesthero.com:999/hls/sky4nz.m3u8?md5=giLC_UY8CsIm7mFElQpfRw&expires=1761951301"
    },
    {
      "tvg-id": "sky5nz",
      "tvg-logo": "https://raw.githubusercontent.com/abusaeeidx/Tv-Channel-Logo/heads/main/CricHD/runded/56-by-xfireflix.png",
      "name": " Sky Sport 5 NZ",
      "url": "https://d15.epicquesthero.com:999/hls/sky5nz.m3u8?md5=30BgVhItVCQOs_9B3O_CLQ&expires=1761951301"
    },
    {
      "tvg-id": "sky6nz",
      "tvg-logo": "https://raw.githubusercontent.com/abusaeeidx/Tv-Channel-Logo/heads/main/CricHD/runded/56-by-xfireflix.png",
      "name": " Sky Sport 6 NZ",
      "url": "https://d12.epicquesthero.com:999/hls/sky6nz.m3u8?md5=BZw70cFclmF0KsKjG8t1ZA&expires=1761951301"
    },
    {
      "tvg-id": "sky7nz",
      "tvg-logo": "https://raw.githubusercontent.com/abusaeeidx/Tv-Channel-Logo/heads/main/CricHD/runded/56-by-xfireflix.png",
      "name": " Sky Sport 7 NZ",
      "url": "https://d15.epicquesthero.com:999/hls/sky7nz.m3u8?md5=maXQnq6wuys4Xkrh9xv8-A&expires=1761951301"
    },
    {
      "tvg-id": "sky8nz",
      "tvg-logo": "https://raw.githubusercontent.com/abusaeeidx/Tv-Channel-Logo/heads/main/CricHD/runded/56-by-xfireflix.png",
      "name": " Sky Sport 8 NZ",
      "url": "https://d13.epicquesthero.com:999/hls/sky8nz.m3u8?md5=MEXLUy_fL567Jp2LkIIULA&expires=1761951301"
    },
    {
      "tvg-id": "laligauk",
      "tvg-logo": "https://raw.githubusercontent.com/abusaeeidx/Tv-Channel-Logo/heads/main/CricHD/runded/19-by-xfireflix.png",
      "name": "LaLiga UK",
      "url": "https://d12.epicquesthero.com:999/hls/laligauk.m3u8?md5=KfFeCEd35BEqzi5xLCcZFw&expires=1761951301"
    },
    {
      "tvg-id": "skysfotb",
      "tvg-logo": "https://raw.githubusercontent.com/abusaeeidx/Tv-Channel-Logo/heads/main/CricHD/runded/44-by-xfireflix.png",
      "name": " Sky Sports Football",
      "url": "https://d12.epicquesthero.com:999/hls/skysfott.m3u8?md5=urilBz_sTBRPl1ZuEmLwBA&expires=1761951296"
    },
    {
      "tvg-id": "hdchnl2",
      "tvg-logo": "https://raw.githubusercontent.com/abusaeeidx/Tv-Channel-Logo/heads/main/CricHD/runded/31-by-xfireflix.png",
      "name": " Premier Sports 2",
      "url": null
    }
  ]
}